{"nodes": [{"id": "ui_src_lib_server_config_ts", "label": "config.ts", "file_type": "code", "source_file": "ui/src/lib/server/config.ts", "source_location": "L1"}, {"id": "config_tryloadenvfile", "label": "tryLoadEnvFile()", "file_type": "code", "source_file": "ui/src/lib/server/config.ts", "source_location": "L8"}, {"id": "config_loadserverenv", "label": "loadServerEnv()", "file_type": "code", "source_file": "ui/src/lib/server/config.ts", "source_location": "L15"}, {"id": "config_ensureserverdirectories", "label": "ensureServerDirectories()", "file_type": "code", "source_file": "ui/src/lib/server/config.ts", "source_location": "L45"}], "edges": [{"source": "ui_src_lib_server_config_ts", "target": "node_fs", "relation": "imports_from", "confidence": "EXTRACTED", "source_file": "ui/src/lib/server/config.ts", "source_location": "L1", "weight": 1.0}, {"source": "ui_src_lib_server_config_ts", "target": "node_path", "relation": "imports_from", "confidence": "EXTRACTED", "source_file": "ui/src/lib/server/config.ts", "source_location": "L2", "weight": 1.0}, {"source": "ui_src_lib_server_config_ts", "target": "dotenv", "relation": "imports_from", "confidence": "EXTRACTED", "source_file": "ui/src/lib/server/config.ts", "source_location": "L4", "weight": 1.0}, {"source": "ui_src_lib_server_config_ts", "target": "config_tryloadenvfile", "relation": "contains", "confidence": "EXTRACTED", "source_file": "ui/src/lib/server/config.ts", "source_location": "L8", "weight": 1.0}, {"source": "ui_src_lib_server_config_ts", "target": "config_loadserverenv", "relation": "contains", "confidence": "EXTRACTED", "source_file": "ui/src/lib/server/config.ts", "source_location": "L15", "weight": 1.0}, {"source": "ui_src_lib_server_config_ts", "target": "config_ensureserverdirectories", "relation": "contains", "confidence": "EXTRACTED", "source_file": "ui/src/lib/server/config.ts", "source_location": "L45", "weight": 1.0}, {"source": "config_loadserverenv", "target": "config_tryloadenvfile", "relation": "calls", "confidence": "EXTRACTED", "source_file": "ui/src/lib/server/config.ts", "source_location": "L23", "weight": 1.0}]}